{
    "/assets/js/vendor.js": "/assets/js/vendor.js?id=e2837e68e9f3e3d37727",
    "/assets/js/vendor.js.map": "/assets/js/vendor.js.map?id=cfb34d2142b1c972c064",
    "/assets/js/app.js": "/assets/js/app.js?id=e0bb07b7e5091de544bb",
    "/assets/css/app.css": "/assets/css/app.css?id=bae8f7b49b5c2b5e5e04",
    "/assets/js/app.js.map": "/assets/js/app.js.map?id=61006f95d8412e2a6de0",
    "/assets/css/app.css.map": "/assets/css/app.css.map?id=907a8bed2c8a5d044484",
    "/assets/js/manifest.js": "/assets/js/manifest.js?id=bb58468fac8d92ddbd39",
    "/assets/js/manifest.js.map": "/assets/js/manifest.js.map?id=b4c2de757b5be83dd62c"
}
